wicked_expressions/__init__.py
wicked_expressions/modules/api.bolt
wicked_expressions/modules/comparison.bolt
wicked_expressions/modules/config.bolt
wicked_expressions/modules/copy_args.bolt
wicked_expressions/modules/internal_api.bolt
wicked_expressions/modules/loader.bolt
wicked_expressions/modules/loader_components.bolt
wicked_expressions/modules/operations.bolt
wicked_expressions/modules/raw_operation.bolt
wicked_expressions/modules/rebindable.bolt
wicked_expressions/modules/sources.bolt
wicked_expressions/modules/utils.bolt
wicked_expressions/modules/var.bolt
wicked_expressions/modules/var_sources.bolt
wicked_expressions/modules/var_types.bolt
wicked_expressions/py.typed
wicked_expressions-1.6.3.dist-info/LICENSE
wicked_expressions-1.6.3.dist-info/METADATA
wicked_expressions-1.6.3.dist-info/WHEEL
wicked_expressions-1.6.3.dist-info/RECORD
