Metadata-Version: 2.1
Name: wicked_expressions
Version: 1.6.3
Summary: Extension of bolt-expressions written in Bolt.
Home-page: https://github.com/reapermc/wicked-expressions
License: MIT
Keywords: beet,bolt,minecraft,minecraft-commands,mcfunction
Author: Yeti
Author-email: arcticyeti1@gmail.com
Requires-Python: >=3.12,<4.0
Classifier: License :: OSI Approved :: MIT License
Classifier: Programming Language :: Python :: 3
Classifier: Programming Language :: Python :: 3.12
Requires-Dist: beet (>=0.89.1)
Requires-Dist: bolt (>=0.36.0)
Requires-Dist: bolt-expressions (>=0.12.2)
Requires-Dist: mecha (>=0.73.0)
